{"page":22,"verse_range":"2:142 → 2:145","juz_numbers":[2],"lines":[{"line_number":1,"half":"A","words":[{"global_id":79368,"order":1,"location":"2:142:1","verse_key":"2:142","position":1,"char_type":"word","line_number":1,"page_number":22,"text_qpc_hafs":"۞ سَيَقُولُ","code_v2":"ﱁ ﱂ"},{"global_id":79369,"order":2,"location":"2:142:2","verse_key":"2:142","position":2,"char_type":"word","line_number":1,"page_number":22,"text_qpc_hafs":"ٱلسُّفَهَآءُ","code_v2":"ﱃ"},{"global_id":79370,"order":3,"location":"2:142:3","verse_key":"2:142","position":3,"char_type":"word","line_number":1,"page_number":22,"text_qpc_hafs":"مِنَ","code_v2":"ﱄ"},{"global_id":79371,"order":4,"location":"2:142:4","verse_key":"2:142","position":4,"char_type":"word","line_number":1,"page_number":22,"text_qpc_hafs":"ٱلنَّاسِ","code_v2":"ﱅ"},{"global_id":79372,"order":5,"location":"2:142:5","verse_key":"2:142","position":5,"char_type":"word","line_number":1,"page_number":22,"text_qpc_hafs":"مَا","code_v2":"ﱆ"},{"global_id":79373,"order":6,"location":"2:142:6","verse_key":"2:142","position":6,"char_type":"word","line_number":1,"page_number":22,"text_qpc_hafs":"وَلَّىٰهُمۡ","code_v2":"ﱇ"},{"global_id":79374,"order":7,"location":"2:142:7","verse_key":"2:142","position":7,"char_type":"word","line_number":1,"page_number":22,"text_qpc_hafs":"عَن","code_v2":"ﱈ"},{"global_id":79375,"order":8,"location":"2:142:8","verse_key":"2:142","position":8,"char_type":"word","line_number":1,"page_number":22,"text_qpc_hafs":"قِبۡلَتِهِمُ","code_v2":"ﱉ"},{"global_id":79376,"order":9,"location":"2:142:9","verse_key":"2:142","position":9,"char_type":"word","line_number":1,"page_number":22,"text_qpc_hafs":"ٱلَّتِي","code_v2":"ﱊ"},{"global_id":79377,"order":10,"location":"2:142:10","verse_key":"2:142","position":10,"char_type":"word","line_number":1,"page_number":22,"text_qpc_hafs":"كَانُواْ","code_v2":"ﱋ"}]},{"line_number":2,"half":"A","words":[{"global_id":79378,"order":11,"location":"2:142:11","verse_key":"2:142","position":11,"char_type":"word","line_number":2,"page_number":22,"text_qpc_hafs":"عَلَيۡهَاۚ","code_v2":"ﱌﱍ"},{"global_id":79380,"order":12,"location":"2:142:12","verse_key":"2:142","position":12,"char_type":"word","line_number":2,"page_number":22,"text_qpc_hafs":"قُل","code_v2":"ﱎ"},{"global_id":79381,"order":13,"location":"2:142:13","verse_key":"2:142","position":13,"char_type":"word","line_number":2,"page_number":22,"text_qpc_hafs":"لِّلَّهِ","code_v2":"ﱏ"},{"global_id":79382,"order":14,"location":"2:142:14","verse_key":"2:142","position":14,"char_type":"word","line_number":2,"page_number":22,"text_qpc_hafs":"ٱلۡمَشۡرِقُ","code_v2":"ﱐ"},{"global_id":79383,"order":15,"location":"2:142:15","verse_key":"2:142","position":15,"char_type":"word","line_number":2,"page_number":22,"text_qpc_hafs":"وَٱلۡمَغۡرِبُۚ","code_v2":"ﱑﱒ"},{"global_id":79385,"order":16,"location":"2:142:16","verse_key":"2:142","position":16,"char_type":"word","line_number":2,"page_number":22,"text_qpc_hafs":"يَهۡدِي","code_v2":"ﱓ"},{"global_id":79386,"order":17,"location":"2:142:17","verse_key":"2:142","position":17,"char_type":"word","line_number":2,"page_number":22,"text_qpc_hafs":"مَن","code_v2":"ﱔ"},{"global_id":79387,"order":18,"location":"2:142:18","verse_key":"2:142","position":18,"char_type":"word","line_number":2,"page_number":22,"text_qpc_hafs":"يَشَآءُ","code_v2":"ﱕ"},{"global_id":79388,"order":19,"location":"2:142:19","verse_key":"2:142","position":19,"char_type":"word","line_number":2,"page_number":22,"text_qpc_hafs":"إِلَىٰ","code_v2":"ﱖ"},{"global_id":79389,"order":20,"location":"2:142:20","verse_key":"2:142","position":20,"char_type":"word","line_number":2,"page_number":22,"text_qpc_hafs":"صِرَٰطٖ","code_v2":"ﱗ"}]},{"line_number":3,"half":"A","words":[{"global_id":79390,"order":21,"location":"2:142:21","verse_key":"2:142","position":21,"char_type":"word","line_number":3,"page_number":22,"text_qpc_hafs":"مُّسۡتَقِيمٖ","code_v2":"ﱘ"},{"global_id":79391,"order":22,"location":"2:142:end","verse_key":"2:142","position":22,"char_type":"end","line_number":3,"page_number":22,"text_qpc_hafs":"١٤٢","code_v2":"ﱙ"},{"global_id":79459,"order":23,"location":"2:143:1","verse_key":"2:143","position":1,"char_type":"word","line_number":3,"page_number":22,"text_qpc_hafs":"وَكَذَٰلِكَ","code_v2":"ﱚ"},{"global_id":79460,"order":24,"location":"2:143:2","verse_key":"2:143","position":2,"char_type":"word","line_number":3,"page_number":22,"text_qpc_hafs":"جَعَلۡنَٰكُمۡ","code_v2":"ﱛ"},{"global_id":79461,"order":25,"location":"2:143:3","verse_key":"2:143","position":3,"char_type":"word","line_number":3,"page_number":22,"text_qpc_hafs":"أُمَّةٗ","code_v2":"ﱜ"},{"global_id":79462,"order":26,"location":"2:143:4","verse_key":"2:143","position":4,"char_type":"word","line_number":3,"page_number":22,"text_qpc_hafs":"وَسَطٗا","code_v2":"ﱝ"},{"global_id":79463,"order":27,"location":"2:143:5","verse_key":"2:143","position":5,"char_type":"word","line_number":3,"page_number":22,"text_qpc_hafs":"لِّتَكُونُواْ","code_v2":"ﱞ"}]},{"line_number":4,"half":"A","words":[{"global_id":79464,"order":28,"location":"2:143:6","verse_key":"2:143","position":6,"char_type":"word","line_number":4,"page_number":22,"text_qpc_hafs":"شُهَدَآءَ","code_v2":"ﱟ"},{"global_id":79465,"order":29,"location":"2:143:7","verse_key":"2:143","position":7,"char_type":"word","line_number":4,"page_number":22,"text_qpc_hafs":"عَلَى","code_v2":"ﱠ"},{"global_id":79466,"order":30,"location":"2:143:8","verse_key":"2:143","position":8,"char_type":"word","line_number":4,"page_number":22,"text_qpc_hafs":"ٱلنَّاسِ","code_v2":"ﱡ"},{"global_id":79467,"order":31,"location":"2:143:9","verse_key":"2:143","position":9,"char_type":"word","line_number":4,"page_number":22,"text_qpc_hafs":"وَيَكُونَ","code_v2":"ﱢ"},{"global_id":79468,"order":32,"location":"2:143:10","verse_key":"2:143","position":10,"char_type":"word","line_number":4,"page_number":22,"text_qpc_hafs":"ٱلرَّسُولُ","code_v2":"ﱣ"},{"global_id":79469,"order":33,"location":"2:143:11","verse_key":"2:143","position":11,"char_type":"word","line_number":4,"page_number":22,"text_qpc_hafs":"عَلَيۡكُمۡ","code_v2":"ﱤ"},{"global_id":79470,"order":34,"location":"2:143:12","verse_key":"2:143","position":12,"char_type":"word","line_number":4,"page_number":22,"text_qpc_hafs":"شَهِيدٗاۗ","code_v2":"ﱥﱦ"},{"global_id":79472,"order":35,"location":"2:143:13","verse_key":"2:143","position":13,"char_type":"word","line_number":4,"page_number":22,"text_qpc_hafs":"وَمَا","code_v2":"ﱧ"}]},{"line_number":5,"half":"A","words":[{"global_id":79473,"order":36,"location":"2:143:14","verse_key":"2:143","position":14,"char_type":"word","line_number":5,"page_number":22,"text_qpc_hafs":"جَعَلۡنَا","code_v2":"ﱨ"},{"global_id":79474,"order":37,"location":"2:143:15","verse_key":"2:143","position":15,"char_type":"word","line_number":5,"page_number":22,"text_qpc_hafs":"ٱلۡقِبۡلَةَ","code_v2":"ﱩ"},{"global_id":79475,"order":38,"location":"2:143:16","verse_key":"2:143","position":16,"char_type":"word","line_number":5,"page_number":22,"text_qpc_hafs":"ٱلَّتِي","code_v2":"ﱪ"},{"global_id":79476,"order":39,"location":"2:143:17","verse_key":"2:143","position":17,"char_type":"word","line_number":5,"page_number":22,"text_qpc_hafs":"كُنتَ","code_v2":"ﱫ"},{"global_id":79477,"order":40,"location":"2:143:18","verse_key":"2:143","position":18,"char_type":"word","line_number":5,"page_number":22,"text_qpc_hafs":"عَلَيۡهَآ","code_v2":"ﱬ"},{"global_id":79478,"order":41,"location":"2:143:19","verse_key":"2:143","position":19,"char_type":"word","line_number":5,"page_number":22,"text_qpc_hafs":"إِلَّا","code_v2":"ﱭ"},{"global_id":79479,"order":42,"location":"2:143:20","verse_key":"2:143","position":20,"char_type":"word","line_number":5,"page_number":22,"text_qpc_hafs":"لِنَعۡلَمَ","code_v2":"ﱮ"},{"global_id":79480,"order":43,"location":"2:143:21","verse_key":"2:143","position":21,"char_type":"word","line_number":5,"page_number":22,"text_qpc_hafs":"مَن","code_v2":"ﱯ"},{"global_id":79481,"order":44,"location":"2:143:22","verse_key":"2:143","position":22,"char_type":"word","line_number":5,"page_number":22,"text_qpc_hafs":"يَتَّبِعُ","code_v2":"ﱰ"},{"global_id":79482,"order":45,"location":"2:143:23","verse_key":"2:143","position":23,"char_type":"word","line_number":5,"page_number":22,"text_qpc_hafs":"ٱلرَّسُولَ","code_v2":"ﱱ"}]},{"line_number":6,"half":"A","words":[{"global_id":79483,"order":46,"location":"2:143:24","verse_key":"2:143","position":24,"char_type":"word","line_number":6,"page_number":22,"text_qpc_hafs":"مِمَّن","code_v2":"ﱲ"},{"global_id":79484,"order":47,"location":"2:143:25","verse_key":"2:143","position":25,"char_type":"word","line_number":6,"page_number":22,"text_qpc_hafs":"يَنقَلِبُ","code_v2":"ﱳ"},{"global_id":79485,"order":48,"location":"2:143:26","verse_key":"2:143","position":26,"char_type":"word","line_number":6,"page_number":22,"text_qpc_hafs":"عَلَىٰ","code_v2":"ﱴ"},{"global_id":79486,"order":49,"location":"2:143:27","verse_key":"2:143","position":27,"char_type":"word","line_number":6,"page_number":22,"text_qpc_hafs":"عَقِبَيۡهِۚ","code_v2":"ﱵﱶ"},{"global_id":79488,"order":50,"location":"2:143:28","verse_key":"2:143","position":28,"char_type":"word","line_number":6,"page_number":22,"text_qpc_hafs":"وَإِن","code_v2":"ﱷ"},{"global_id":79489,"order":51,"location":"2:143:29","verse_key":"2:143","position":29,"char_type":"word","line_number":6,"page_number":22,"text_qpc_hafs":"كَانَتۡ","code_v2":"ﱸ"},{"global_id":79490,"order":52,"location":"2:143:30","verse_key":"2:143","position":30,"char_type":"word","line_number":6,"page_number":22,"text_qpc_hafs":"لَكَبِيرَةً","code_v2":"ﱹ"},{"global_id":79491,"order":53,"location":"2:143:31","verse_key":"2:143","position":31,"char_type":"word","line_number":6,"page_number":22,"text_qpc_hafs":"إِلَّا","code_v2":"ﱺ"},{"global_id":79492,"order":54,"location":"2:143:32","verse_key":"2:143","position":32,"char_type":"word","line_number":6,"page_number":22,"text_qpc_hafs":"عَلَى","code_v2":"ﱻ"},{"global_id":79493,"order":55,"location":"2:143:33","verse_key":"2:143","position":33,"char_type":"word","line_number":6,"page_number":22,"text_qpc_hafs":"ٱلَّذِينَ","code_v2":"ﱼ"}]},{"line_number":7,"half":"A","words":[{"global_id":79494,"order":56,"location":"2:143:34","verse_key":"2:143","position":34,"char_type":"word","line_number":7,"page_number":22,"text_qpc_hafs":"هَدَى","code_v2":"ﱽ"},{"global_id":79495,"order":57,"location":"2:143:35","verse_key":"2:143","position":35,"char_type":"word","line_number":7,"page_number":22,"text_qpc_hafs":"ٱللَّهُۗ","code_v2":"ﱾﱿ"},{"global_id":79497,"order":58,"location":"2:143:36","verse_key":"2:143","position":36,"char_type":"word","line_number":7,"page_number":22,"text_qpc_hafs":"وَمَا","code_v2":"ﲀ"},{"global_id":79498,"order":59,"location":"2:143:37","verse_key":"2:143","position":37,"char_type":"word","line_number":7,"page_number":22,"text_qpc_hafs":"كَانَ","code_v2":"ﲁ"},{"global_id":79499,"order":60,"location":"2:143:38","verse_key":"2:143","position":38,"char_type":"word","line_number":7,"page_number":22,"text_qpc_hafs":"ٱللَّهُ","code_v2":"ﲂ"},{"global_id":79500,"order":61,"location":"2:143:39","verse_key":"2:143","position":39,"char_type":"word","line_number":7,"page_number":22,"text_qpc_hafs":"لِيُضِيعَ","code_v2":"ﲃ"},{"global_id":79501,"order":62,"location":"2:143:40","verse_key":"2:143","position":40,"char_type":"word","line_number":7,"page_number":22,"text_qpc_hafs":"إِيمَٰنَكُمۡۚ","code_v2":"ﲄﲅ"},{"global_id":79503,"order":63,"location":"2:143:41","verse_key":"2:143","position":41,"char_type":"word","line_number":7,"page_number":22,"text_qpc_hafs":"إِنَّ","code_v2":"ﲆ"},{"global_id":79504,"order":64,"location":"2:143:42","verse_key":"2:143","position":42,"char_type":"word","line_number":7,"page_number":22,"text_qpc_hafs":"ٱللَّهَ","code_v2":"ﲇ"}]},{"line_number":8,"half":"B","words":[{"global_id":79505,"order":65,"location":"2:143:43","verse_key":"2:143","position":43,"char_type":"word","line_number":8,"page_number":22,"text_qpc_hafs":"بِٱلنَّاسِ","code_v2":"ﲈ"},{"global_id":79506,"order":66,"location":"2:143:44","verse_key":"2:143","position":44,"char_type":"word","line_number":8,"page_number":22,"text_qpc_hafs":"لَرَءُوفٞ","code_v2":"ﲉ"},{"global_id":79507,"order":67,"location":"2:143:45","verse_key":"2:143","position":45,"char_type":"word","line_number":8,"page_number":22,"text_qpc_hafs":"رَّحِيمٞ","code_v2":"ﲊ"},{"global_id":79508,"order":68,"location":"2:143:end","verse_key":"2:143","position":46,"char_type":"end","line_number":8,"page_number":22,"text_qpc_hafs":"١٤٣","code_v2":"ﲋ"},{"global_id":79706,"order":69,"location":"2:144:1","verse_key":"2:144","position":1,"char_type":"word","line_number":8,"page_number":22,"text_qpc_hafs":"قَدۡ","code_v2":"ﲌ"},{"global_id":79707,"order":70,"location":"2:144:2","verse_key":"2:144","position":2,"char_type":"word","line_number":8,"page_number":22,"text_qpc_hafs":"نَرَىٰ","code_v2":"ﲍ"},{"global_id":79708,"order":71,"location":"2:144:3","verse_key":"2:144","position":3,"char_type":"word","line_number":8,"page_number":22,"text_qpc_hafs":"تَقَلُّبَ","code_v2":"ﲎ"},{"global_id":79709,"order":72,"location":"2:144:4","verse_key":"2:144","position":4,"char_type":"word","line_number":8,"page_number":22,"text_qpc_hafs":"وَجۡهِكَ","code_v2":"ﲏ"},{"global_id":79710,"order":73,"location":"2:144:5","verse_key":"2:144","position":5,"char_type":"word","line_number":8,"page_number":22,"text_qpc_hafs":"فِي","code_v2":"ﲐ"},{"global_id":79711,"order":74,"location":"2:144:6","verse_key":"2:144","position":6,"char_type":"word","line_number":8,"page_number":22,"text_qpc_hafs":"ٱلسَّمَآءِۖ","code_v2":"ﲑﲒ"}]},{"line_number":9,"half":"B","words":[{"global_id":79713,"order":75,"location":"2:144:7","verse_key":"2:144","position":7,"char_type":"word","line_number":9,"page_number":22,"text_qpc_hafs":"فَلَنُوَلِّيَنَّكَ","code_v2":"ﲓ"},{"global_id":79714,"order":76,"location":"2:144:8","verse_key":"2:144","position":8,"char_type":"word","line_number":9,"page_number":22,"text_qpc_hafs":"قِبۡلَةٗ","code_v2":"ﲔ"},{"global_id":79715,"order":77,"location":"2:144:9","verse_key":"2:144","position":9,"char_type":"word","line_number":9,"page_number":22,"text_qpc_hafs":"تَرۡضَىٰهَاۚ","code_v2":"ﲕﲖ"},{"global_id":79717,"order":78,"location":"2:144:10","verse_key":"2:144","position":10,"char_type":"word","line_number":9,"page_number":22,"text_qpc_hafs":"فَوَلِّ","code_v2":"ﲗ"},{"global_id":79718,"order":79,"location":"2:144:11","verse_key":"2:144","position":11,"char_type":"word","line_number":9,"page_number":22,"text_qpc_hafs":"وَجۡهَكَ","code_v2":"ﲘ"},{"global_id":79719,"order":80,"location":"2:144:12","verse_key":"2:144","position":12,"char_type":"word","line_number":9,"page_number":22,"text_qpc_hafs":"شَطۡرَ","code_v2":"ﲙ"},{"global_id":79720,"order":81,"location":"2:144:13","verse_key":"2:144","position":13,"char_type":"word","line_number":9,"page_number":22,"text_qpc_hafs":"ٱلۡمَسۡجِدِ","code_v2":"ﲚ"}]},{"line_number":10,"half":"B","words":[{"global_id":79721,"order":82,"location":"2:144:14","verse_key":"2:144","position":14,"char_type":"word","line_number":10,"page_number":22,"text_qpc_hafs":"ٱلۡحَرَامِۚ","code_v2":"ﲛﲜ"},{"global_id":79723,"order":83,"location":"2:144:15","verse_key":"2:144","position":15,"char_type":"word","line_number":10,"page_number":22,"text_qpc_hafs":"وَحَيۡثُ","code_v2":"ﲝ"},{"global_id":79724,"order":84,"location":"2:144:16","verse_key":"2:144","position":16,"char_type":"word","line_number":10,"page_number":22,"text_qpc_hafs":"مَا","code_v2":"ﲞ"},{"global_id":79725,"order":85,"location":"2:144:17","verse_key":"2:144","position":17,"char_type":"word","line_number":10,"page_number":22,"text_qpc_hafs":"كُنتُمۡ","code_v2":"ﲟ"},{"global_id":79726,"order":86,"location":"2:144:18","verse_key":"2:144","position":18,"char_type":"word","line_number":10,"page_number":22,"text_qpc_hafs":"فَوَلُّواْ","code_v2":"ﲠ"},{"global_id":79727,"order":87,"location":"2:144:19","verse_key":"2:144","position":19,"char_type":"word","line_number":10,"page_number":22,"text_qpc_hafs":"وُجُوهَكُمۡ","code_v2":"ﲡ"},{"global_id":79728,"order":88,"location":"2:144:20","verse_key":"2:144","position":20,"char_type":"word","line_number":10,"page_number":22,"text_qpc_hafs":"شَطۡرَهُۥۗ","code_v2":"ﲢﲣ"},{"global_id":79730,"order":89,"location":"2:144:21","verse_key":"2:144","position":21,"char_type":"word","line_number":10,"page_number":22,"text_qpc_hafs":"وَإِنَّ","code_v2":"ﲤ"}]},{"line_number":11,"half":"B","words":[{"global_id":79731,"order":90,"location":"2:144:22","verse_key":"2:144","position":22,"char_type":"word","line_number":11,"page_number":22,"text_qpc_hafs":"ٱلَّذِينَ","code_v2":"ﲥ"},{"global_id":79732,"order":91,"location":"2:144:23","verse_key":"2:144","position":23,"char_type":"word","line_number":11,"page_number":22,"text_qpc_hafs":"أُوتُواْ","code_v2":"ﲦ"},{"global_id":79733,"order":92,"location":"2:144:24","verse_key":"2:144","position":24,"char_type":"word","line_number":11,"page_number":22,"text_qpc_hafs":"ٱلۡكِتَٰبَ","code_v2":"ﲧ"},{"global_id":79734,"order":93,"location":"2:144:25","verse_key":"2:144","position":25,"char_type":"word","line_number":11,"page_number":22,"text_qpc_hafs":"لَيَعۡلَمُونَ","code_v2":"ﲨ"},{"global_id":79735,"order":94,"location":"2:144:26","verse_key":"2:144","position":26,"char_type":"word","line_number":11,"page_number":22,"text_qpc_hafs":"أَنَّهُ","code_v2":"ﲩ"},{"global_id":79736,"order":95,"location":"2:144:27","verse_key":"2:144","position":27,"char_type":"word","line_number":11,"page_number":22,"text_qpc_hafs":"ٱلۡحَقُّ","code_v2":"ﲪ"},{"global_id":79737,"order":96,"location":"2:144:28","verse_key":"2:144","position":28,"char_type":"word","line_number":11,"page_number":22,"text_qpc_hafs":"مِن","code_v2":"ﲫ"},{"global_id":79738,"order":97,"location":"2:144:29","verse_key":"2:144","position":29,"char_type":"word","line_number":11,"page_number":22,"text_qpc_hafs":"رَّبِّهِمۡۗ","code_v2":"ﲬﲭ"},{"global_id":79740,"order":98,"location":"2:144:30","verse_key":"2:144","position":30,"char_type":"word","line_number":11,"page_number":22,"text_qpc_hafs":"وَمَا","code_v2":"ﲮ"},{"global_id":79741,"order":99,"location":"2:144:31","verse_key":"2:144","position":31,"char_type":"word","line_number":11,"page_number":22,"text_qpc_hafs":"ٱللَّهُ","code_v2":"ﲯ"}]},{"line_number":12,"half":"B","words":[{"global_id":79742,"order":100,"location":"2:144:32","verse_key":"2:144","position":32,"char_type":"word","line_number":12,"page_number":22,"text_qpc_hafs":"بِغَٰفِلٍ","code_v2":"ﲰ"},{"global_id":79743,"order":101,"location":"2:144:33","verse_key":"2:144","position":33,"char_type":"word","line_number":12,"page_number":22,"text_qpc_hafs":"عَمَّا","code_v2":"ﲱ"},{"global_id":79744,"order":102,"location":"2:144:34","verse_key":"2:144","position":34,"char_type":"word","line_number":12,"page_number":22,"text_qpc_hafs":"يَعۡمَلُونَ","code_v2":"ﲲ"},{"global_id":79745,"order":103,"location":"2:144:end","verse_key":"2:144","position":35,"char_type":"end","line_number":12,"page_number":22,"text_qpc_hafs":"١٤٤","code_v2":"ﲳ"},{"global_id":79792,"order":104,"location":"2:145:1","verse_key":"2:145","position":1,"char_type":"word","line_number":12,"page_number":22,"text_qpc_hafs":"وَلَئِنۡ","code_v2":"ﲴ"},{"global_id":79793,"order":105,"location":"2:145:2","verse_key":"2:145","position":2,"char_type":"word","line_number":12,"page_number":22,"text_qpc_hafs":"أَتَيۡتَ","code_v2":"ﲵ"},{"global_id":79794,"order":106,"location":"2:145:3","verse_key":"2:145","position":3,"char_type":"word","line_number":12,"page_number":22,"text_qpc_hafs":"ٱلَّذِينَ","code_v2":"ﲶ"},{"global_id":79795,"order":107,"location":"2:145:4","verse_key":"2:145","position":4,"char_type":"word","line_number":12,"page_number":22,"text_qpc_hafs":"أُوتُواْ","code_v2":"ﲷ"},{"global_id":79796,"order":108,"location":"2:145:5","verse_key":"2:145","position":5,"char_type":"word","line_number":12,"page_number":22,"text_qpc_hafs":"ٱلۡكِتَٰبَ","code_v2":"ﲸ"}]},{"line_number":13,"half":"B","words":[{"global_id":79797,"order":109,"location":"2:145:6","verse_key":"2:145","position":6,"char_type":"word","line_number":13,"page_number":22,"text_qpc_hafs":"بِكُلِّ","code_v2":"ﲹ"},{"global_id":79798,"order":110,"location":"2:145:7","verse_key":"2:145","position":7,"char_type":"word","line_number":13,"page_number":22,"text_qpc_hafs":"ءَايَةٖ","code_v2":"ﲺ"},{"global_id":79799,"order":111,"location":"2:145:8","verse_key":"2:145","position":8,"char_type":"word","line_number":13,"page_number":22,"text_qpc_hafs":"مَّا","code_v2":"ﲻ"},{"global_id":79800,"order":112,"location":"2:145:9","verse_key":"2:145","position":9,"char_type":"word","line_number":13,"page_number":22,"text_qpc_hafs":"تَبِعُواْ","code_v2":"ﲼ"},{"global_id":79801,"order":113,"location":"2:145:10","verse_key":"2:145","position":10,"char_type":"word","line_number":13,"page_number":22,"text_qpc_hafs":"قِبۡلَتَكَۚ","code_v2":"ﲽﲾ"},{"global_id":79803,"order":114,"location":"2:145:11","verse_key":"2:145","position":11,"char_type":"word","line_number":13,"page_number":22,"text_qpc_hafs":"وَمَآ","code_v2":"ﲿ"},{"global_id":79804,"order":115,"location":"2:145:12","verse_key":"2:145","position":12,"char_type":"word","line_number":13,"page_number":22,"text_qpc_hafs":"أَنتَ","code_v2":"ﳀ"},{"global_id":79805,"order":116,"location":"2:145:13","verse_key":"2:145","position":13,"char_type":"word","line_number":13,"page_number":22,"text_qpc_hafs":"بِتَابِعٖ","code_v2":"ﳁ"},{"global_id":79806,"order":117,"location":"2:145:14","verse_key":"2:145","position":14,"char_type":"word","line_number":13,"page_number":22,"text_qpc_hafs":"قِبۡلَتَهُمۡۚ","code_v2":"ﳂﳃ"}]},{"line_number":14,"half":"B","words":[{"global_id":79808,"order":118,"location":"2:145:15","verse_key":"2:145","position":15,"char_type":"word","line_number":14,"page_number":22,"text_qpc_hafs":"وَمَا","code_v2":"ﳄ"},{"global_id":79809,"order":119,"location":"2:145:16","verse_key":"2:145","position":16,"char_type":"word","line_number":14,"page_number":22,"text_qpc_hafs":"بَعۡضُهُم","code_v2":"ﳅ"},{"global_id":79810,"order":120,"location":"2:145:17","verse_key":"2:145","position":17,"char_type":"word","line_number":14,"page_number":22,"text_qpc_hafs":"بِتَابِعٖ","code_v2":"ﳆ"},{"global_id":79811,"order":121,"location":"2:145:18","verse_key":"2:145","position":18,"char_type":"word","line_number":14,"page_number":22,"text_qpc_hafs":"قِبۡلَةَ","code_v2":"ﳇ"},{"global_id":79812,"order":122,"location":"2:145:19","verse_key":"2:145","position":19,"char_type":"word","line_number":14,"page_number":22,"text_qpc_hafs":"بَعۡضٖۚ","code_v2":"ﳈﳉ"},{"global_id":79814,"order":123,"location":"2:145:20","verse_key":"2:145","position":20,"char_type":"word","line_number":14,"page_number":22,"text_qpc_hafs":"وَلَئِنِ","code_v2":"ﳊ"},{"global_id":79815,"order":124,"location":"2:145:21","verse_key":"2:145","position":21,"char_type":"word","line_number":14,"page_number":22,"text_qpc_hafs":"ٱتَّبَعۡتَ","code_v2":"ﳋ"},{"global_id":79816,"order":125,"location":"2:145:22","verse_key":"2:145","position":22,"char_type":"word","line_number":14,"page_number":22,"text_qpc_hafs":"أَهۡوَآءَهُم","code_v2":"ﳌ"},{"global_id":79817,"order":126,"location":"2:145:23","verse_key":"2:145","position":23,"char_type":"word","line_number":14,"page_number":22,"text_qpc_hafs":"مِّنۢ","code_v2":"ﳍ"}]},{"line_number":15,"half":"B","words":[{"global_id":79818,"order":127,"location":"2:145:24","verse_key":"2:145","position":24,"char_type":"word","line_number":15,"page_number":22,"text_qpc_hafs":"بَعۡدِ","code_v2":"ﳎ"},{"global_id":79819,"order":128,"location":"2:145:25","verse_key":"2:145","position":25,"char_type":"word","line_number":15,"page_number":22,"text_qpc_hafs":"مَا","code_v2":"ﳏ"},{"global_id":79820,"order":129,"location":"2:145:26","verse_key":"2:145","position":26,"char_type":"word","line_number":15,"page_number":22,"text_qpc_hafs":"جَآءَكَ","code_v2":"ﳐ"},{"global_id":79821,"order":130,"location":"2:145:27","verse_key":"2:145","position":27,"char_type":"word","line_number":15,"page_number":22,"text_qpc_hafs":"مِنَ","code_v2":"ﳑ"},{"global_id":79822,"order":131,"location":"2:145:28","verse_key":"2:145","position":28,"char_type":"word","line_number":15,"page_number":22,"text_qpc_hafs":"ٱلۡعِلۡمِ","code_v2":"ﳒ"},{"global_id":79824,"order":132,"location":"2:145:29","verse_key":"2:145","position":29,"char_type":"word","line_number":15,"page_number":22,"text_qpc_hafs":"إِنَّكَ","code_v2":"ﳓ"},{"global_id":79825,"order":133,"location":"2:145:30","verse_key":"2:145","position":30,"char_type":"word","line_number":15,"page_number":22,"text_qpc_hafs":"إِذٗا","code_v2":"ﳔ"},{"global_id":79826,"order":134,"location":"2:145:31","verse_key":"2:145","position":31,"char_type":"word","line_number":15,"page_number":22,"text_qpc_hafs":"لَّمِنَ","code_v2":"ﳕ"},{"global_id":79827,"order":135,"location":"2:145:32","verse_key":"2:145","position":32,"char_type":"word","line_number":15,"page_number":22,"text_qpc_hafs":"ٱلظَّٰلِمِينَ","code_v2":"ﳖ"},{"global_id":79828,"order":136,"location":"2:145:end","verse_key":"2:145","position":33,"char_type":"end","line_number":15,"page_number":22,"text_qpc_hafs":"١٤٥","code_v2":"ﳗ"}]}]}