{"page":349,"verse_range":"23:105 → 23:118","juz_numbers":[18],"lines":[{"line_number":1,"half":"A","words":[{"global_id":72847,"order":1,"location":"23:105:1","verse_key":"23:105","position":1,"char_type":"word","line_number":1,"page_number":349,"text_qpc_hafs":"أَلَمۡ","code_v2":"ﱁ"},{"global_id":72848,"order":2,"location":"23:105:2","verse_key":"23:105","position":2,"char_type":"word","line_number":1,"page_number":349,"text_qpc_hafs":"تَكُنۡ","code_v2":"ﱂ"},{"global_id":72849,"order":3,"location":"23:105:3","verse_key":"23:105","position":3,"char_type":"word","line_number":1,"page_number":349,"text_qpc_hafs":"ءَايَٰتِي","code_v2":"ﱃ"},{"global_id":72850,"order":4,"location":"23:105:4","verse_key":"23:105","position":4,"char_type":"word","line_number":1,"page_number":349,"text_qpc_hafs":"تُتۡلَىٰ","code_v2":"ﱄ"},{"global_id":72851,"order":5,"location":"23:105:5","verse_key":"23:105","position":5,"char_type":"word","line_number":1,"page_number":349,"text_qpc_hafs":"عَلَيۡكُمۡ","code_v2":"ﱅ"},{"global_id":72852,"order":6,"location":"23:105:6","verse_key":"23:105","position":6,"char_type":"word","line_number":1,"page_number":349,"text_qpc_hafs":"فَكُنتُم","code_v2":"ﱆ"},{"global_id":72853,"order":7,"location":"23:105:7","verse_key":"23:105","position":7,"char_type":"word","line_number":1,"page_number":349,"text_qpc_hafs":"بِهَا","code_v2":"ﱇ"},{"global_id":72854,"order":8,"location":"23:105:8","verse_key":"23:105","position":8,"char_type":"word","line_number":1,"page_number":349,"text_qpc_hafs":"تُكَذِّبُونَ","code_v2":"ﱈ"},{"global_id":72855,"order":9,"location":"23:105:end","verse_key":"23:105","position":9,"char_type":"end","line_number":1,"page_number":349,"text_qpc_hafs":"١٠٥","code_v2":"ﱉ"},{"global_id":73049,"order":10,"location":"23:106:1","verse_key":"23:106","position":1,"char_type":"word","line_number":1,"page_number":349,"text_qpc_hafs":"قَالُواْ","code_v2":"ﱊ"}]},{"line_number":2,"half":"A","words":[{"global_id":73050,"order":11,"location":"23:106:2","verse_key":"23:106","position":2,"char_type":"word","line_number":2,"page_number":349,"text_qpc_hafs":"رَبَّنَا","code_v2":"ﱋ"},{"global_id":73051,"order":12,"location":"23:106:3","verse_key":"23:106","position":3,"char_type":"word","line_number":2,"page_number":349,"text_qpc_hafs":"غَلَبَتۡ","code_v2":"ﱌ"},{"global_id":73052,"order":13,"location":"23:106:4","verse_key":"23:106","position":4,"char_type":"word","line_number":2,"page_number":349,"text_qpc_hafs":"عَلَيۡنَا","code_v2":"ﱍ"},{"global_id":73053,"order":14,"location":"23:106:5","verse_key":"23:106","position":5,"char_type":"word","line_number":2,"page_number":349,"text_qpc_hafs":"شِقۡوَتُنَا","code_v2":"ﱎ"},{"global_id":73054,"order":15,"location":"23:106:6","verse_key":"23:106","position":6,"char_type":"word","line_number":2,"page_number":349,"text_qpc_hafs":"وَكُنَّا","code_v2":"ﱏ"},{"global_id":73055,"order":16,"location":"23:106:7","verse_key":"23:106","position":7,"char_type":"word","line_number":2,"page_number":349,"text_qpc_hafs":"قَوۡمٗا","code_v2":"ﱐ"},{"global_id":73056,"order":17,"location":"23:106:8","verse_key":"23:106","position":8,"char_type":"word","line_number":2,"page_number":349,"text_qpc_hafs":"ضَآلِّينَ","code_v2":"ﱑ"},{"global_id":73057,"order":18,"location":"23:106:end","verse_key":"23:106","position":9,"char_type":"end","line_number":2,"page_number":349,"text_qpc_hafs":"١٠٦","code_v2":"ﱒ"},{"global_id":73187,"order":19,"location":"23:107:1","verse_key":"23:107","position":1,"char_type":"word","line_number":2,"page_number":349,"text_qpc_hafs":"رَبَّنَآ","code_v2":"ﱓ"}]},{"line_number":3,"half":"A","words":[{"global_id":73188,"order":20,"location":"23:107:2","verse_key":"23:107","position":2,"char_type":"word","line_number":3,"page_number":349,"text_qpc_hafs":"أَخۡرِجۡنَا","code_v2":"ﱔ"},{"global_id":73189,"order":21,"location":"23:107:3","verse_key":"23:107","position":3,"char_type":"word","line_number":3,"page_number":349,"text_qpc_hafs":"مِنۡهَا","code_v2":"ﱕ"},{"global_id":73190,"order":22,"location":"23:107:4","verse_key":"23:107","position":4,"char_type":"word","line_number":3,"page_number":349,"text_qpc_hafs":"فَإِنۡ","code_v2":"ﱖ"},{"global_id":73191,"order":23,"location":"23:107:5","verse_key":"23:107","position":5,"char_type":"word","line_number":3,"page_number":349,"text_qpc_hafs":"عُدۡنَا","code_v2":"ﱗ"},{"global_id":73192,"order":24,"location":"23:107:6","verse_key":"23:107","position":6,"char_type":"word","line_number":3,"page_number":349,"text_qpc_hafs":"فَإِنَّا","code_v2":"ﱘ"},{"global_id":73193,"order":25,"location":"23:107:7","verse_key":"23:107","position":7,"char_type":"word","line_number":3,"page_number":349,"text_qpc_hafs":"ظَٰلِمُونَ","code_v2":"ﱙ"},{"global_id":73194,"order":26,"location":"23:107:end","verse_key":"23:107","position":8,"char_type":"end","line_number":3,"page_number":349,"text_qpc_hafs":"١٠٧","code_v2":"ﱚ"},{"global_id":73700,"order":27,"location":"23:108:1","verse_key":"23:108","position":1,"char_type":"word","line_number":3,"page_number":349,"text_qpc_hafs":"قَالَ","code_v2":"ﱛ"},{"global_id":73701,"order":28,"location":"23:108:2","verse_key":"23:108","position":2,"char_type":"word","line_number":3,"page_number":349,"text_qpc_hafs":"ٱخۡسَـُٔواْ","code_v2":"ﱜ"},{"global_id":73702,"order":29,"location":"23:108:3","verse_key":"23:108","position":3,"char_type":"word","line_number":3,"page_number":349,"text_qpc_hafs":"فِيهَا","code_v2":"ﱝ"}]},{"line_number":4,"half":"A","words":[{"global_id":73703,"order":30,"location":"23:108:4","verse_key":"23:108","position":4,"char_type":"word","line_number":4,"page_number":349,"text_qpc_hafs":"وَلَا","code_v2":"ﱞ"},{"global_id":73704,"order":31,"location":"23:108:5","verse_key":"23:108","position":5,"char_type":"word","line_number":4,"page_number":349,"text_qpc_hafs":"تُكَلِّمُونِ","code_v2":"ﱟ"},{"global_id":73705,"order":32,"location":"23:108:end","verse_key":"23:108","position":6,"char_type":"end","line_number":4,"page_number":349,"text_qpc_hafs":"١٠٨","code_v2":"ﱠ"},{"global_id":73870,"order":33,"location":"23:109:1","verse_key":"23:109","position":1,"char_type":"word","line_number":4,"page_number":349,"text_qpc_hafs":"إِنَّهُۥ","code_v2":"ﱡ"},{"global_id":73871,"order":34,"location":"23:109:2","verse_key":"23:109","position":2,"char_type":"word","line_number":4,"page_number":349,"text_qpc_hafs":"كَانَ","code_v2":"ﱢ"},{"global_id":73872,"order":35,"location":"23:109:3","verse_key":"23:109","position":3,"char_type":"word","line_number":4,"page_number":349,"text_qpc_hafs":"فَرِيقٞ","code_v2":"ﱣ"},{"global_id":73873,"order":36,"location":"23:109:4","verse_key":"23:109","position":4,"char_type":"word","line_number":4,"page_number":349,"text_qpc_hafs":"مِّنۡ","code_v2":"ﱤ"},{"global_id":73874,"order":37,"location":"23:109:5","verse_key":"23:109","position":5,"char_type":"word","line_number":4,"page_number":349,"text_qpc_hafs":"عِبَادِي","code_v2":"ﱥ"},{"global_id":73875,"order":38,"location":"23:109:6","verse_key":"23:109","position":6,"char_type":"word","line_number":4,"page_number":349,"text_qpc_hafs":"يَقُولُونَ","code_v2":"ﱦ"},{"global_id":73876,"order":39,"location":"23:109:7","verse_key":"23:109","position":7,"char_type":"word","line_number":4,"page_number":349,"text_qpc_hafs":"رَبَّنَآ","code_v2":"ﱧ"},{"global_id":73877,"order":40,"location":"23:109:8","verse_key":"23:109","position":8,"char_type":"word","line_number":4,"page_number":349,"text_qpc_hafs":"ءَامَنَّا","code_v2":"ﱨ"}]},{"line_number":5,"half":"A","words":[{"global_id":73878,"order":41,"location":"23:109:9","verse_key":"23:109","position":9,"char_type":"word","line_number":5,"page_number":349,"text_qpc_hafs":"فَٱغۡفِرۡ","code_v2":"ﱩ"},{"global_id":73879,"order":42,"location":"23:109:10","verse_key":"23:109","position":10,"char_type":"word","line_number":5,"page_number":349,"text_qpc_hafs":"لَنَا","code_v2":"ﱪ"},{"global_id":73880,"order":43,"location":"23:109:11","verse_key":"23:109","position":11,"char_type":"word","line_number":5,"page_number":349,"text_qpc_hafs":"وَٱرۡحَمۡنَا","code_v2":"ﱫ"},{"global_id":73881,"order":44,"location":"23:109:12","verse_key":"23:109","position":12,"char_type":"word","line_number":5,"page_number":349,"text_qpc_hafs":"وَأَنتَ","code_v2":"ﱬ"},{"global_id":73882,"order":45,"location":"23:109:13","verse_key":"23:109","position":13,"char_type":"word","line_number":5,"page_number":349,"text_qpc_hafs":"خَيۡرُ","code_v2":"ﱭ"},{"global_id":73883,"order":46,"location":"23:109:14","verse_key":"23:109","position":14,"char_type":"word","line_number":5,"page_number":349,"text_qpc_hafs":"ٱلرَّٰحِمِينَ","code_v2":"ﱮ"},{"global_id":73884,"order":47,"location":"23:109:end","verse_key":"23:109","position":15,"char_type":"end","line_number":5,"page_number":349,"text_qpc_hafs":"١٠٩","code_v2":"ﱯ"},{"global_id":74041,"order":48,"location":"23:110:1","verse_key":"23:110","position":1,"char_type":"word","line_number":5,"page_number":349,"text_qpc_hafs":"فَٱتَّخَذۡتُمُوهُمۡ","code_v2":"ﱰ"}]},{"line_number":6,"half":"A","words":[{"global_id":74042,"order":49,"location":"23:110:2","verse_key":"23:110","position":2,"char_type":"word","line_number":6,"page_number":349,"text_qpc_hafs":"سِخۡرِيًّا","code_v2":"ﱱ"},{"global_id":74043,"order":50,"location":"23:110:3","verse_key":"23:110","position":3,"char_type":"word","line_number":6,"page_number":349,"text_qpc_hafs":"حَتَّىٰٓ","code_v2":"ﱲ"},{"global_id":74044,"order":51,"location":"23:110:4","verse_key":"23:110","position":4,"char_type":"word","line_number":6,"page_number":349,"text_qpc_hafs":"أَنسَوۡكُمۡ","code_v2":"ﱳ"},{"global_id":74045,"order":52,"location":"23:110:5","verse_key":"23:110","position":5,"char_type":"word","line_number":6,"page_number":349,"text_qpc_hafs":"ذِكۡرِي","code_v2":"ﱴ"},{"global_id":74046,"order":53,"location":"23:110:6","verse_key":"23:110","position":6,"char_type":"word","line_number":6,"page_number":349,"text_qpc_hafs":"وَكُنتُم","code_v2":"ﱵ"},{"global_id":74047,"order":54,"location":"23:110:7","verse_key":"23:110","position":7,"char_type":"word","line_number":6,"page_number":349,"text_qpc_hafs":"مِّنۡهُمۡ","code_v2":"ﱶ"},{"global_id":74048,"order":55,"location":"23:110:8","verse_key":"23:110","position":8,"char_type":"word","line_number":6,"page_number":349,"text_qpc_hafs":"تَضۡحَكُونَ","code_v2":"ﱷ"},{"global_id":74049,"order":56,"location":"23:110:end","verse_key":"23:110","position":9,"char_type":"end","line_number":6,"page_number":349,"text_qpc_hafs":"١١٠","code_v2":"ﱸ"}]},{"line_number":7,"half":"A","words":[{"global_id":74468,"order":57,"location":"23:111:1","verse_key":"23:111","position":1,"char_type":"word","line_number":7,"page_number":349,"text_qpc_hafs":"إِنِّي","code_v2":"ﱹ"},{"global_id":74469,"order":58,"location":"23:111:2","verse_key":"23:111","position":2,"char_type":"word","line_number":7,"page_number":349,"text_qpc_hafs":"جَزَيۡتُهُمُ","code_v2":"ﱺ"},{"global_id":74470,"order":59,"location":"23:111:3","verse_key":"23:111","position":3,"char_type":"word","line_number":7,"page_number":349,"text_qpc_hafs":"ٱلۡيَوۡمَ","code_v2":"ﱻ"},{"global_id":74471,"order":60,"location":"23:111:4","verse_key":"23:111","position":4,"char_type":"word","line_number":7,"page_number":349,"text_qpc_hafs":"بِمَا","code_v2":"ﱼ"},{"global_id":74472,"order":61,"location":"23:111:5","verse_key":"23:111","position":5,"char_type":"word","line_number":7,"page_number":349,"text_qpc_hafs":"صَبَرُوٓاْ","code_v2":"ﱽ"},{"global_id":74473,"order":62,"location":"23:111:6","verse_key":"23:111","position":6,"char_type":"word","line_number":7,"page_number":349,"text_qpc_hafs":"أَنَّهُمۡ","code_v2":"ﱾ"},{"global_id":74474,"order":63,"location":"23:111:7","verse_key":"23:111","position":7,"char_type":"word","line_number":7,"page_number":349,"text_qpc_hafs":"هُمُ","code_v2":"ﱿ"},{"global_id":74475,"order":64,"location":"23:111:8","verse_key":"23:111","position":8,"char_type":"word","line_number":7,"page_number":349,"text_qpc_hafs":"ٱلۡفَآئِزُونَ","code_v2":"ﲀ"},{"global_id":74476,"order":65,"location":"23:111:end","verse_key":"23:111","position":9,"char_type":"end","line_number":7,"page_number":349,"text_qpc_hafs":"١١١","code_v2":"ﲁ"},{"global_id":74825,"order":66,"location":"23:112:1","verse_key":"23:112","position":1,"char_type":"word","line_number":7,"page_number":349,"text_qpc_hafs":"قَٰلَ","code_v2":"ﲂ"}]},{"line_number":8,"half":"B","words":[{"global_id":74826,"order":67,"location":"23:112:2","verse_key":"23:112","position":2,"char_type":"word","line_number":8,"page_number":349,"text_qpc_hafs":"كَمۡ","code_v2":"ﲃ"},{"global_id":74827,"order":68,"location":"23:112:3","verse_key":"23:112","position":3,"char_type":"word","line_number":8,"page_number":349,"text_qpc_hafs":"لَبِثۡتُمۡ","code_v2":"ﲄ"},{"global_id":74828,"order":69,"location":"23:112:4","verse_key":"23:112","position":4,"char_type":"word","line_number":8,"page_number":349,"text_qpc_hafs":"فِي","code_v2":"ﲅ"},{"global_id":74829,"order":70,"location":"23:112:5","verse_key":"23:112","position":5,"char_type":"word","line_number":8,"page_number":349,"text_qpc_hafs":"ٱلۡأَرۡضِ","code_v2":"ﲆ"},{"global_id":74830,"order":71,"location":"23:112:6","verse_key":"23:112","position":6,"char_type":"word","line_number":8,"page_number":349,"text_qpc_hafs":"عَدَدَ","code_v2":"ﲇ"},{"global_id":74831,"order":72,"location":"23:112:7","verse_key":"23:112","position":7,"char_type":"word","line_number":8,"page_number":349,"text_qpc_hafs":"سِنِينَ","code_v2":"ﲈ"},{"global_id":74832,"order":73,"location":"23:112:end","verse_key":"23:112","position":8,"char_type":"end","line_number":8,"page_number":349,"text_qpc_hafs":"١١٢","code_v2":"ﲉ"},{"global_id":75022,"order":74,"location":"23:113:1","verse_key":"23:113","position":1,"char_type":"word","line_number":8,"page_number":349,"text_qpc_hafs":"قَالُواْ","code_v2":"ﲊ"},{"global_id":75023,"order":75,"location":"23:113:2","verse_key":"23:113","position":2,"char_type":"word","line_number":8,"page_number":349,"text_qpc_hafs":"لَبِثۡنَا","code_v2":"ﲋ"},{"global_id":75024,"order":76,"location":"23:113:3","verse_key":"23:113","position":3,"char_type":"word","line_number":8,"page_number":349,"text_qpc_hafs":"يَوۡمًا","code_v2":"ﲌ"},{"global_id":75025,"order":77,"location":"23:113:4","verse_key":"23:113","position":4,"char_type":"word","line_number":8,"page_number":349,"text_qpc_hafs":"أَوۡ","code_v2":"ﲍ"},{"global_id":75026,"order":78,"location":"23:113:5","verse_key":"23:113","position":5,"char_type":"word","line_number":8,"page_number":349,"text_qpc_hafs":"بَعۡضَ","code_v2":"ﲎ"}]},{"line_number":9,"half":"B","words":[{"global_id":75027,"order":79,"location":"23:113:6","verse_key":"23:113","position":6,"char_type":"word","line_number":9,"page_number":349,"text_qpc_hafs":"يَوۡمٖ","code_v2":"ﲏ"},{"global_id":75028,"order":80,"location":"23:113:7","verse_key":"23:113","position":7,"char_type":"word","line_number":9,"page_number":349,"text_qpc_hafs":"فَسۡـَٔلِ","code_v2":"ﲐ"},{"global_id":75029,"order":81,"location":"23:113:8","verse_key":"23:113","position":8,"char_type":"word","line_number":9,"page_number":349,"text_qpc_hafs":"ٱلۡعَآدِّينَ","code_v2":"ﲑ"},{"global_id":75030,"order":82,"location":"23:113:end","verse_key":"23:113","position":9,"char_type":"end","line_number":9,"page_number":349,"text_qpc_hafs":"١١٣","code_v2":"ﲒ"},{"global_id":75185,"order":83,"location":"23:114:1","verse_key":"23:114","position":1,"char_type":"word","line_number":9,"page_number":349,"text_qpc_hafs":"قَٰلَ","code_v2":"ﲓ"},{"global_id":75186,"order":84,"location":"23:114:2","verse_key":"23:114","position":2,"char_type":"word","line_number":9,"page_number":349,"text_qpc_hafs":"إِن","code_v2":"ﲔ"},{"global_id":75187,"order":85,"location":"23:114:3","verse_key":"23:114","position":3,"char_type":"word","line_number":9,"page_number":349,"text_qpc_hafs":"لَّبِثۡتُمۡ","code_v2":"ﲕ"},{"global_id":75188,"order":86,"location":"23:114:4","verse_key":"23:114","position":4,"char_type":"word","line_number":9,"page_number":349,"text_qpc_hafs":"إِلَّا","code_v2":"ﲖ"},{"global_id":75189,"order":87,"location":"23:114:5","verse_key":"23:114","position":5,"char_type":"word","line_number":9,"page_number":349,"text_qpc_hafs":"قَلِيلٗاۖ","code_v2":"ﲗﲘ"},{"global_id":75191,"order":88,"location":"23:114:6","verse_key":"23:114","position":6,"char_type":"word","line_number":9,"page_number":349,"text_qpc_hafs":"لَّوۡ","code_v2":"ﲙ"},{"global_id":75192,"order":89,"location":"23:114:7","verse_key":"23:114","position":7,"char_type":"word","line_number":9,"page_number":349,"text_qpc_hafs":"أَنَّكُمۡ","code_v2":"ﲚ"}]},{"line_number":10,"half":"B","words":[{"global_id":75193,"order":90,"location":"23:114:8","verse_key":"23:114","position":8,"char_type":"word","line_number":10,"page_number":349,"text_qpc_hafs":"كُنتُمۡ","code_v2":"ﲛ"},{"global_id":75194,"order":91,"location":"23:114:9","verse_key":"23:114","position":9,"char_type":"word","line_number":10,"page_number":349,"text_qpc_hafs":"تَعۡلَمُونَ","code_v2":"ﲜ"},{"global_id":75195,"order":92,"location":"23:114:end","verse_key":"23:114","position":10,"char_type":"end","line_number":10,"page_number":349,"text_qpc_hafs":"١١٤","code_v2":"ﲝ"},{"global_id":75383,"order":93,"location":"23:115:1","verse_key":"23:115","position":1,"char_type":"word","line_number":10,"page_number":349,"text_qpc_hafs":"أَفَحَسِبۡتُمۡ","code_v2":"ﲞ"},{"global_id":75384,"order":94,"location":"23:115:2","verse_key":"23:115","position":2,"char_type":"word","line_number":10,"page_number":349,"text_qpc_hafs":"أَنَّمَا","code_v2":"ﲟ"},{"global_id":75385,"order":95,"location":"23:115:3","verse_key":"23:115","position":3,"char_type":"word","line_number":10,"page_number":349,"text_qpc_hafs":"خَلَقۡنَٰكُمۡ","code_v2":"ﲠ"},{"global_id":75386,"order":96,"location":"23:115:4","verse_key":"23:115","position":4,"char_type":"word","line_number":10,"page_number":349,"text_qpc_hafs":"عَبَثٗا","code_v2":"ﲡ"},{"global_id":75387,"order":97,"location":"23:115:5","verse_key":"23:115","position":5,"char_type":"word","line_number":10,"page_number":349,"text_qpc_hafs":"وَأَنَّكُمۡ","code_v2":"ﲢ"}]},{"line_number":11,"half":"B","words":[{"global_id":75388,"order":98,"location":"23:115:6","verse_key":"23:115","position":6,"char_type":"word","line_number":11,"page_number":349,"text_qpc_hafs":"إِلَيۡنَا","code_v2":"ﲣ"},{"global_id":75389,"order":99,"location":"23:115:7","verse_key":"23:115","position":7,"char_type":"word","line_number":11,"page_number":349,"text_qpc_hafs":"لَا","code_v2":"ﲤ"},{"global_id":75390,"order":100,"location":"23:115:8","verse_key":"23:115","position":8,"char_type":"word","line_number":11,"page_number":349,"text_qpc_hafs":"تُرۡجَعُونَ","code_v2":"ﲥ"},{"global_id":75391,"order":101,"location":"23:115:end","verse_key":"23:115","position":9,"char_type":"end","line_number":11,"page_number":349,"text_qpc_hafs":"١١٥","code_v2":"ﲦ"},{"global_id":75653,"order":102,"location":"23:116:1","verse_key":"23:116","position":1,"char_type":"word","line_number":11,"page_number":349,"text_qpc_hafs":"فَتَعَٰلَى","code_v2":"ﲧ"},{"global_id":75654,"order":103,"location":"23:116:2","verse_key":"23:116","position":2,"char_type":"word","line_number":11,"page_number":349,"text_qpc_hafs":"ٱللَّهُ","code_v2":"ﲨ"},{"global_id":75655,"order":104,"location":"23:116:3","verse_key":"23:116","position":3,"char_type":"word","line_number":11,"page_number":349,"text_qpc_hafs":"ٱلۡمَلِكُ","code_v2":"ﲩ"},{"global_id":75656,"order":105,"location":"23:116:4","verse_key":"23:116","position":4,"char_type":"word","line_number":11,"page_number":349,"text_qpc_hafs":"ٱلۡحَقُّۖ","code_v2":"ﲪﲫ"},{"global_id":75658,"order":106,"location":"23:116:5","verse_key":"23:116","position":5,"char_type":"word","line_number":11,"page_number":349,"text_qpc_hafs":"لَآ","code_v2":"ﲬ"},{"global_id":75659,"order":107,"location":"23:116:6","verse_key":"23:116","position":6,"char_type":"word","line_number":11,"page_number":349,"text_qpc_hafs":"إِلَٰهَ","code_v2":"ﲭ"},{"global_id":75660,"order":108,"location":"23:116:7","verse_key":"23:116","position":7,"char_type":"word","line_number":11,"page_number":349,"text_qpc_hafs":"إِلَّا","code_v2":"ﲮ"}]},{"line_number":12,"half":"B","words":[{"global_id":75661,"order":109,"location":"23:116:8","verse_key":"23:116","position":8,"char_type":"word","line_number":12,"page_number":349,"text_qpc_hafs":"هُوَ","code_v2":"ﲯ"},{"global_id":75662,"order":110,"location":"23:116:9","verse_key":"23:116","position":9,"char_type":"word","line_number":12,"page_number":349,"text_qpc_hafs":"رَبُّ","code_v2":"ﲰ"},{"global_id":75663,"order":111,"location":"23:116:10","verse_key":"23:116","position":10,"char_type":"word","line_number":12,"page_number":349,"text_qpc_hafs":"ٱلۡعَرۡشِ","code_v2":"ﲱ"},{"global_id":75664,"order":112,"location":"23:116:11","verse_key":"23:116","position":11,"char_type":"word","line_number":12,"page_number":349,"text_qpc_hafs":"ٱلۡكَرِيمِ","code_v2":"ﲲ"},{"global_id":75665,"order":113,"location":"23:116:end","verse_key":"23:116","position":12,"char_type":"end","line_number":12,"page_number":349,"text_qpc_hafs":"١١٦","code_v2":"ﲳ"},{"global_id":75821,"order":114,"location":"23:117:1","verse_key":"23:117","position":1,"char_type":"word","line_number":12,"page_number":349,"text_qpc_hafs":"وَمَن","code_v2":"ﲴ"},{"global_id":75822,"order":115,"location":"23:117:2","verse_key":"23:117","position":2,"char_type":"word","line_number":12,"page_number":349,"text_qpc_hafs":"يَدۡعُ","code_v2":"ﲵ"},{"global_id":75823,"order":116,"location":"23:117:3","verse_key":"23:117","position":3,"char_type":"word","line_number":12,"page_number":349,"text_qpc_hafs":"مَعَ","code_v2":"ﲶ"},{"global_id":75824,"order":117,"location":"23:117:4","verse_key":"23:117","position":4,"char_type":"word","line_number":12,"page_number":349,"text_qpc_hafs":"ٱللَّهِ","code_v2":"ﲷ"},{"global_id":75825,"order":118,"location":"23:117:5","verse_key":"23:117","position":5,"char_type":"word","line_number":12,"page_number":349,"text_qpc_hafs":"إِلَٰهًا","code_v2":"ﲸ"}]},{"line_number":13,"half":"B","words":[{"global_id":75826,"order":119,"location":"23:117:6","verse_key":"23:117","position":6,"char_type":"word","line_number":13,"page_number":349,"text_qpc_hafs":"ءَاخَرَ","code_v2":"ﲹ"},{"global_id":75827,"order":120,"location":"23:117:7","verse_key":"23:117","position":7,"char_type":"word","line_number":13,"page_number":349,"text_qpc_hafs":"لَا","code_v2":"ﲺ"},{"global_id":75828,"order":121,"location":"23:117:8","verse_key":"23:117","position":8,"char_type":"word","line_number":13,"page_number":349,"text_qpc_hafs":"بُرۡهَٰنَ","code_v2":"ﲻ"},{"global_id":75829,"order":122,"location":"23:117:9","verse_key":"23:117","position":9,"char_type":"word","line_number":13,"page_number":349,"text_qpc_hafs":"لَهُۥ","code_v2":"ﲼ"},{"global_id":75830,"order":123,"location":"23:117:10","verse_key":"23:117","position":10,"char_type":"word","line_number":13,"page_number":349,"text_qpc_hafs":"بِهِۦ","code_v2":"ﲽ"},{"global_id":75831,"order":124,"location":"23:117:11","verse_key":"23:117","position":11,"char_type":"word","line_number":13,"page_number":349,"text_qpc_hafs":"فَإِنَّمَا","code_v2":"ﲾ"},{"global_id":75832,"order":125,"location":"23:117:12","verse_key":"23:117","position":12,"char_type":"word","line_number":13,"page_number":349,"text_qpc_hafs":"حِسَابُهُۥ","code_v2":"ﲿ"},{"global_id":75833,"order":126,"location":"23:117:13","verse_key":"23:117","position":13,"char_type":"word","line_number":13,"page_number":349,"text_qpc_hafs":"عِندَ","code_v2":"ﳀ"},{"global_id":75834,"order":127,"location":"23:117:14","verse_key":"23:117","position":14,"char_type":"word","line_number":13,"page_number":349,"text_qpc_hafs":"رَبِّهِۦٓۚ","code_v2":"ﳁﳂ"},{"global_id":75836,"order":128,"location":"23:117:15","verse_key":"23:117","position":15,"char_type":"word","line_number":13,"page_number":349,"text_qpc_hafs":"إِنَّهُۥ","code_v2":"ﳃ"},{"global_id":75837,"order":129,"location":"23:117:16","verse_key":"23:117","position":16,"char_type":"word","line_number":13,"page_number":349,"text_qpc_hafs":"لَا","code_v2":"ﳄ"},{"global_id":75838,"order":130,"location":"23:117:17","verse_key":"23:117","position":17,"char_type":"word","line_number":13,"page_number":349,"text_qpc_hafs":"يُفۡلِحُ","code_v2":"ﳅ"}]},{"line_number":14,"half":"B","words":[{"global_id":75839,"order":131,"location":"23:117:18","verse_key":"23:117","position":18,"char_type":"word","line_number":14,"page_number":349,"text_qpc_hafs":"ٱلۡكَٰفِرُونَ","code_v2":"ﳆ"},{"global_id":75840,"order":132,"location":"23:117:end","verse_key":"23:117","position":19,"char_type":"end","line_number":14,"page_number":349,"text_qpc_hafs":"١١٧","code_v2":"ﳇ"},{"global_id":76095,"order":133,"location":"23:118:1","verse_key":"23:118","position":1,"char_type":"word","line_number":14,"page_number":349,"text_qpc_hafs":"وَقُل","code_v2":"ﳈ"},{"global_id":76096,"order":134,"location":"23:118:2","verse_key":"23:118","position":2,"char_type":"word","line_number":14,"page_number":349,"text_qpc_hafs":"رَّبِّ","code_v2":"ﳉ"},{"global_id":76097,"order":135,"location":"23:118:3","verse_key":"23:118","position":3,"char_type":"word","line_number":14,"page_number":349,"text_qpc_hafs":"ٱغۡفِرۡ","code_v2":"ﳊ"},{"global_id":76098,"order":136,"location":"23:118:4","verse_key":"23:118","position":4,"char_type":"word","line_number":14,"page_number":349,"text_qpc_hafs":"وَٱرۡحَمۡ","code_v2":"ﳋ"},{"global_id":76099,"order":137,"location":"23:118:5","verse_key":"23:118","position":5,"char_type":"word","line_number":14,"page_number":349,"text_qpc_hafs":"وَأَنتَ","code_v2":"ﳌ"},{"global_id":76100,"order":138,"location":"23:118:6","verse_key":"23:118","position":6,"char_type":"word","line_number":14,"page_number":349,"text_qpc_hafs":"خَيۡرُ","code_v2":"ﳍ"},{"global_id":76101,"order":139,"location":"23:118:7","verse_key":"23:118","position":7,"char_type":"word","line_number":14,"page_number":349,"text_qpc_hafs":"ٱلرَّٰحِمِينَ","code_v2":"ﳎ"},{"global_id":76102,"order":140,"location":"23:118:end","verse_key":"23:118","position":8,"char_type":"end","line_number":14,"page_number":349,"text_qpc_hafs":"١١٨","code_v2":"ﳏ"}]}]}